crimpy/__init__.py
crimpy/crimpy.py
crimpy/folium.py
crimpy-0.0.4.dist-info/LICENSE
crimpy-0.0.4.dist-info/METADATA
crimpy-0.0.4.dist-info/WHEEL
crimpy-0.0.4.dist-info/dependency_links.txt
crimpy-0.0.4.dist-info/top_level.txt
crimpy-0.0.4.dist-info/RECORD
