Metadata-Version: 2.1
Name: crimpy
Version: 0.0.4
Summary: A python package for interactive mapping.
Home-page: https://github.com/statenandrea33/crimpy
Author: Andrea Staten
Author-email: statenandrea33@gmail.com
License: MIT license
Keywords: crimpy
Classifier: Development Status :: 2 - Pre-Alpha
Classifier: Intended Audience :: Developers
Classifier: License :: OSI Approved :: MIT License
Classifier: Natural Language :: English
Classifier: Programming Language :: Python :: 3
Classifier: Programming Language :: Python :: 3.7
Classifier: Programming Language :: Python :: 3.8
Classifier: Programming Language :: Python :: 3.9
Classifier: Programming Language :: Python :: 3.10
Requires-Python: >=3.7
License-File: LICENSE
Requires-Dist: folium
Requires-Dist: ipyleaflet
Requires-Dist: geopandas
Requires-Dist: httpx
